odoo/addons/configurar_compras_en_deposito/README.md
odoo/addons/configurar_compras_en_deposito/__init__.py
odoo/addons/configurar_compras_en_deposito/__manifest__.py
odoo/addons/configurar_compras_en_deposito/models/__init__.py
odoo/addons/configurar_compras_en_deposito/models/configura_datos_compra_en_deposito.py
odoo/addons/configurar_compras_en_deposito/static/description/icon.png
odoo/addons/configurar_compras_en_deposito/views/configura_datos_compra_en_deposito_view.xml
odoo13_addon_configurar_compras_en_deposito-13.0.0.0.1.dist-info/METADATA
odoo13_addon_configurar_compras_en_deposito-13.0.0.0.1.dist-info/WHEEL
odoo13_addon_configurar_compras_en_deposito-13.0.0.0.1.dist-info/top_level.txt
odoo13_addon_configurar_compras_en_deposito-13.0.0.0.1.dist-info/RECORD
